{
  "date": "2026-06-24",
  "run_type": "full",
  "generated": "2026-06-24T19:05:32.418180Z",
  "game_count": 13,
  "ev_pick_count": 1,
  "missing_books": [],
  "model": {
    "version": "v4.0",
    "data_sources": [
      "MLB Stats API \u2014 official 2026 season stats",
      "FIP calculated from HR/BB/HBP/K/IP (standard formula)",
      "wOBA calculated from counting stats (standard linear weights)",
      "FanDuel + BetMGM via The Odds API",
      "OpenWeatherMap live weather",
      "Retrosheet 33,292 game trained lookup"
    ],
    "thresholds": {
      "ev_min": 0.08,
      "win_prob_min": 0.58
    },
    "train_games": 33292
  },
  "observations": [],
  "picks": [
    {
      "game_metadata": {
        "game_id": "2026-06-24-CLE-CWS",
        "game_pk": "824583",
        "home": "CWS",
        "away": "CLE",
        "home_full": "Chicago White Sox",
        "away_full": "Cleveland Guardians",
        "home_sp": "Erick Fedde",
        "away_sp": "Tanner Bibee",
        "start_time": "2026-06-24T18:10:00Z",
        "venue": "Rate Field",
        "park_factor": 1.007,
        "weather": {
          "temp_f": 71.1,
          "wind_mph": 9.9,
          "wind_dir": "SW",
          "condition": "Rain",
          "provisional": false
        },
        "umpire": "Tripp Gibson",
        "lineup_confirmed": true,
        "status": "scheduled",
        "score": "Scheduled",
        "result": null
      },
      "projections": {
        "fair_home_ml": 159,
        "fair_away_ml": -159,
        "fair_home_p": 0.386,
        "fair_away_p": 0.614,
        "fair_f5_p": 0.433,
        "proj_total": 8.4,
        "home_proj_runs": 4.02,
        "away_proj_runs": 4.34,
        "home_woba": 0.3215,
        "away_woba": 0.2905,
        "sp_home_era": 4.46,
        "sp_away_era": 4.64,
        "sp_home_fip": 5.68,
        "sp_away_fip": 6.13,
        "sp_home_k9": 6.11,
        "sp_away_k9": 8.04,
        "sp_home_bb9": 3.44,
        "sp_away_bb9": 2.16,
        "sp_home_whip": 1.39,
        "sp_away_whip": 1.03,
        "sp_home_ip": 70.2,
        "sp_away_ip": 29.1,
        "sp_home_source": "season_2026",
        "sp_away_source": "last_30d",
        "h_bat_source": "last_30d",
        "a_bat_source": "last_30d",
        "h_bull_tax": 0.0,
        "a_bull_tax": 0.0,
        "h_bull_detail": [],
        "a_bull_detail": [],
        "h_home_wr": 0.422,
        "a_away_wr": 0.512,
        "ump_bias": 0.0,
        "mkt_home_p": 0.4955,
        "mkt_away_p": 0.5045,
        "book_lines": {
          "FanDuel": {
            "home_ml": -104,
            "away_ml": -112,
            "pick_ml": -112
          },
          "BetMGM": {
            "home_ml": -110,
            "away_ml": -110,
            "pick_ml": -110
          }
        },
        "best_book": "BetMGM",
        "best_book_ml": -110
      },
      "market_edge": {
        "best_bet": "CLE ML -110 (BetMGM)",
        "f5_bet": null,
        "ev_percent": 10.9,
        "kelly_stake": "4.7%",
        "tier": "TOP",
        "bet_side": "away",
        "signals": [
          "LINEUPS_CONFIRMED",
          "RAIN_RISK"
        ]
      },
      "math": {
        "base_pyth_p": 0.465,
        "prop_adj": -0.0789,
        "ump_adj": 0.0,
        "h_fatigue_tax": 0.0,
        "a_fatigue_tax": 0.0,
        "final_home_p": 0.3861,
        "mkt_home_p": 0.4955,
        "h_home_wr": 0.422,
        "a_away_wr": 0.512,
        "park_factor": 1.007,
        "ump_bias": 0.0,
        "sp_suppress_h": 0.3176,
        "sp_suppress_a": 0.3194
      }
    },
    {
      "game_metadata": {
        "game_id": "2026-06-24-CHC-NYM",
        "game_pk": "823613",
        "home": "NYM",
        "away": "CHC",
        "home_full": "New York Mets",
        "away_full": "Chicago Cubs",
        "home_sp": "Nolan McLean",
        "away_sp": "Javier Assad",
        "start_time": "2026-06-24T17:10:00Z",
        "venue": "Citi Field",
        "park_factor": 1.032,
        "weather": {
          "temp_f": 82.3,
          "wind_mph": 13.0,
          "wind_dir": "NW",
          "condition": "Clear",
          "provisional": false
        },
        "umpire": "Austin Jones",
        "lineup_confirmed": true,
        "status": "scheduled",
        "score": "Scheduled",
        "result": null
      },
      "projections": {
        "fair_home_ml": -117,
        "fair_away_ml": 117,
        "fair_home_p": 0.54,
        "fair_away_p": 0.46,
        "fair_f5_p": 0.533,
        "proj_total": 10.1,
        "home_proj_runs": 5.22,
        "away_proj_runs": 4.9,
        "home_woba": 0.3214,
        "away_woba": 0.3448,
        "sp_home_era": 4.92,
        "sp_away_era": 4.04,
        "sp_home_fip": 4.68,
        "sp_away_fip": 4.8,
        "sp_home_k9": 10.71,
        "sp_away_k9": 5.51,
        "sp_home_bb9": 4.92,
        "sp_away_bb9": 2.02,
        "sp_home_whip": 1.29,
        "sp_away_whip": 1.04,
        "sp_home_ip": 31.1,
        "sp_away_ip": 49.0,
        "sp_home_source": "last_30d",
        "sp_away_source": "season_2026",
        "h_bat_source": "last_30d",
        "a_bat_source": "last_30d",
        "h_bull_tax": 0.0,
        "a_bull_tax": 0.0,
        "h_bull_detail": [],
        "a_bull_detail": [],
        "h_home_wr": 0.566,
        "a_away_wr": 0.475,
        "ump_bias": 0.0,
        "mkt_home_p": 0.5089,
        "mkt_away_p": 0.4911,
        "book_lines": {},
        "best_book": null,
        "best_book_ml": null
      },
      "market_edge": {
        "best_bet": "NO EDGE",
        "f5_bet": null,
        "ev_percent": 0.0,
        "kelly_stake": "0%",
        "tier": "SKIP",
        "bet_side": null,
        "signals": [
          "LINEUPS_CONFIRMED",
          "WIND_13.0mph_NW",
          "SINGLE_BOOK_ONLY"
        ]
      },
      "math": {
        "base_pyth_p": 0.5289,
        "prop_adj": 0.0112,
        "ump_adj": 0.0,
        "h_fatigue_tax": 0.0,
        "a_fatigue_tax": 0.0,
        "final_home_p": 0.5401,
        "mkt_home_p": 0.5089,
        "h_home_wr": 0.566,
        "a_away_wr": 0.475,
        "park_factor": 1.032,
        "ump_bias": 0.0,
        "sp_suppress_h": 0.3222,
        "sp_suppress_a": 0.3134
      }
    },
    {
      "game_metadata": {
        "game_id": "2026-06-24-CHC-NYM",
        "game_pk": "823611",
        "home": "NYM",
        "away": "CHC",
        "home_full": "New York Mets",
        "away_full": "Chicago Cubs",
        "home_sp": "Sean Manaea",
        "away_sp": "Shota Imanaga",
        "start_time": "2026-06-24T23:10:00Z",
        "venue": "Citi Field",
        "park_factor": 1.032,
        "weather": {
          "temp_f": 82.3,
          "wind_mph": 13.0,
          "wind_dir": "NW",
          "condition": "Clear",
          "provisional": false
        },
        "umpire": "TBD",
        "lineup_confirmed": false,
        "status": "scheduled",
        "score": "Scheduled",
        "result": null
      },
      "projections": {
        "fair_home_ml": -115,
        "fair_away_ml": 115,
        "fair_home_p": 0.536,
        "fair_away_p": 0.464,
        "fair_f5_p": 0.529,
        "proj_total": 10.1,
        "home_proj_runs": 5.19,
        "away_proj_runs": 4.92,
        "home_woba": 0.3214,
        "away_woba": 0.3448,
        "sp_home_era": 4.64,
        "sp_away_era": 4.26,
        "sp_home_fip": 3.82,
        "sp_away_fip": 4.65,
        "sp_home_k9": 9.28,
        "sp_away_k9": 8.72,
        "sp_home_bb9": 2.98,
        "sp_away_bb9": 2.28,
        "sp_home_whip": 1.34,
        "sp_away_whip": 1.06,
        "sp_home_ip": 54.1,
        "sp_away_ip": 86.2,
        "sp_home_source": "season_2026",
        "sp_away_source": "season_2026",
        "h_bat_source": "last_30d",
        "a_bat_source": "last_30d",
        "h_bull_tax": 0.0,
        "a_bull_tax": 0.0,
        "h_bull_detail": [],
        "a_bull_detail": [],
        "h_home_wr": 0.566,
        "a_away_wr": 0.475,
        "ump_bias": 0.0,
        "mkt_home_p": 0.5089,
        "mkt_away_p": 0.4911,
        "book_lines": {},
        "best_book": null,
        "best_book_ml": null
      },
      "market_edge": {
        "best_bet": "NO EDGE",
        "f5_bet": null,
        "ev_percent": 0.0,
        "kelly_stake": "0%",
        "tier": "SKIP",
        "bet_side": null,
        "signals": [
          "LINEUP_UNCONFIRMED",
          "WIND_13.0mph_NW",
          "SINGLE_BOOK_ONLY"
        ]
      },
      "math": {
        "base_pyth_p": 0.5244,
        "prop_adj": 0.0112,
        "ump_adj": 0.0,
        "h_fatigue_tax": 0.0,
        "a_fatigue_tax": 0.0,
        "final_home_p": 0.5356,
        "mkt_home_p": 0.5089,
        "h_home_wr": 0.566,
        "a_away_wr": 0.475,
        "park_factor": 1.032,
        "ump_bias": 0.0,
        "sp_suppress_h": 0.3194,
        "sp_suppress_a": 0.3156
      }
    },
    {
      "game_metadata": {
        "game_id": "2026-06-24-BOS-COL",
        "game_pk": "824341",
        "home": "COL",
        "away": "BOS",
        "home_full": "Colorado Rockies",
        "away_full": "Boston Red Sox",
        "home_sp": "Kyle Freeland",
        "away_sp": "Ranger Suarez",
        "start_time": "2026-06-24T19:10:00Z",
        "venue": "Coors Field",
        "park_factor": 1.287,
        "weather": {
          "temp_f": 82.3,
          "wind_mph": 4.0,
          "wind_dir": "NW",
          "condition": "Clouds",
          "provisional": false
        },
        "umpire": "Brennan Miller",
        "lineup_confirmed": true,
        "status": "scheduled",
        "score": "Scheduled",
        "result": null
      },
      "projections": {
        "fair_home_ml": 125,
        "fair_away_ml": -125,
        "fair_home_p": 0.445,
        "fair_away_p": 0.555,
        "fair_f5_p": 0.471,
        "proj_total": 12.7,
        "home_proj_runs": 6.25,
        "away_proj_runs": 6.41,
        "home_woba": 0.3604,
        "away_woba": 0.3138,
        "sp_home_era": 8.15,
        "sp_away_era": 3.96,
        "sp_home_fip": 4.3,
        "sp_away_fip": 2.62,
        "sp_home_k9": 7.47,
        "sp_away_k9": 10.55,
        "sp_home_bb9": 0.68,
        "sp_away_bb9": 3.3,
        "sp_home_whip": 1.47,
        "sp_away_whip": 1.36,
        "sp_home_ip": 26.5,
        "sp_away_ip": 27.3,
        "sp_home_source": "last_30d",
        "sp_away_source": "last_30d",
        "h_bat_source": "last_30d",
        "a_bat_source": "last_30d",
        "h_bull_tax": 0.0,
        "a_bull_tax": 0.0,
        "h_bull_detail": [],
        "a_bull_detail": [],
        "h_home_wr": 0.491,
        "a_away_wr": 0.509,
        "ump_bias": 0.0,
        "mkt_home_p": 0.4016,
        "mkt_away_p": 0.5984,
        "book_lines": {},
        "best_book": null,
        "best_book_ml": null
      },
      "market_edge": {
        "best_bet": "NO EDGE",
        "f5_bet": null,
        "ev_percent": 0.0,
        "kelly_stake": "0%",
        "tier": "SKIP",
        "bet_side": null,
        "signals": [
          "LINEUPS_CONFIRMED",
          "HIGH_PARK_1.29x"
        ]
      },
      "math": {
        "base_pyth_p": 0.4884,
        "prop_adj": -0.043,
        "ump_adj": 0.0,
        "h_fatigue_tax": 0.0,
        "a_fatigue_tax": 0.0,
        "final_home_p": 0.4454,
        "mkt_home_p": 0.4016,
        "h_home_wr": 0.491,
        "a_away_wr": 0.509,
        "park_factor": 1.287,
        "ump_bias": 0.0,
        "sp_suppress_h": 0.3545,
        "sp_suppress_a": 0.3126
      }
    },
    {
      "game_metadata": {
        "game_id": "2026-06-24-BAL-LAA",
        "game_pk": "824018",
        "home": "LAA",
        "away": "BAL",
        "home_full": "Los Angeles Angels",
        "away_full": "Baltimore Orioles",
        "home_sp": "Jos\u00e9 Soriano",
        "away_sp": "Trey Gibson",
        "start_time": "2026-06-24T20:07:00Z",
        "venue": "Angel Stadium",
        "park_factor": 1.0,
        "weather": {
          "temp_f": 77.7,
          "wind_mph": 7.0,
          "wind_dir": "SW",
          "condition": "Clear",
          "provisional": false
        },
        "umpire": "James Hoye",
        "lineup_confirmed": true,
        "status": "scheduled",
        "score": "Scheduled",
        "result": null
      },
      "projections": {
        "fair_home_ml": 126,
        "fair_away_ml": -126,
        "fair_home_p": 0.443,
        "fair_away_p": 0.557,
        "fair_f5_p": 0.467,
        "proj_total": 9.6,
        "home_proj_runs": 4.7,
        "away_proj_runs": 4.87,
        "home_woba": 0.3392,
        "away_woba": 0.3321,
        "sp_home_era": 4.64,
        "sp_away_era": 5.81,
        "sp_home_fip": 6.34,
        "sp_away_fip": 5.7,
        "sp_home_k9": 8.57,
        "sp_away_k9": 6.84,
        "sp_home_bb9": 6.79,
        "sp_away_bb9": 5.81,
        "sp_home_whip": 1.83,
        "sp_away_whip": 1.71,
        "sp_home_ip": 25.2,
        "sp_away_ip": 26.1,
        "sp_home_source": "last_30d",
        "sp_away_source": "season_2026",
        "h_bat_source": "last_30d",
        "a_bat_source": "last_30d",
        "h_bull_tax": 0.0,
        "a_bull_tax": 0.0,
        "h_bull_detail": [],
        "a_bull_detail": [],
        "h_home_wr": 0.449,
        "a_away_wr": 0.462,
        "ump_bias": 0.0,
        "mkt_home_p": 0.5164,
        "mkt_away_p": 0.4836,
        "book_lines": {},
        "best_book": null,
        "best_book_ml": null
      },
      "market_edge": {
        "best_bet": "NO EDGE",
        "f5_bet": null,
        "ev_percent": 0.0,
        "kelly_stake": "0%",
        "tier": "SKIP",
        "bet_side": null,
        "signals": [
          "LINEUPS_CONFIRMED"
        ]
      },
      "math": {
        "base_pyth_p": 0.4838,
        "prop_adj": -0.0409,
        "ump_adj": 0.0,
        "h_fatigue_tax": 0.0,
        "a_fatigue_tax": 0.0,
        "final_home_p": 0.4429,
        "mkt_home_p": 0.5164,
        "h_home_wr": 0.449,
        "a_away_wr": 0.462,
        "park_factor": 1.0,
        "ump_bias": 0.0,
        "sp_suppress_h": 0.3194,
        "sp_suppress_a": 0.3311
      }
    },
    {
      "game_metadata": {
        "game_id": "2026-06-24-SEA-PIT",
        "game_pk": "823367",
        "home": "PIT",
        "away": "SEA",
        "home_full": "Pittsburgh Pirates",
        "away_full": "Seattle Mariners",
        "home_sp": "Braxton Ashcraft",
        "away_sp": "Bryan Woo",
        "start_time": "2026-06-24T22:40:00Z",
        "venue": "PNC Park",
        "park_factor": 1.0,
        "weather": {
          "temp_f": 78.0,
          "wind_mph": 5.0,
          "wind_dir": "NW",
          "condition": "Clear",
          "provisional": false
        },
        "umpire": "Vic Carapazza",
        "lineup_confirmed": false,
        "status": "scheduled",
        "score": "Scheduled",
        "result": null
      },
      "projections": {
        "fair_home_ml": 140,
        "fair_away_ml": -140,
        "fair_home_p": 0.416,
        "fair_away_p": 0.584,
        "fair_f5_p": 0.445,
        "proj_total": 9.3,
        "home_proj_runs": 4.47,
        "away_proj_runs": 4.84,
        "home_woba": 0.3473,
        "away_woba": 0.316,
        "sp_home_era": 3.84,
        "sp_away_era": 4.3,
        "sp_home_fip": 2.78,
        "sp_away_fip": 2.77,
        "sp_home_k9": 10.25,
        "sp_away_k9": 10.4,
        "sp_home_bb9": 1.92,
        "sp_away_bb9": 0.72,
        "sp_home_whip": 1.28,
        "sp_away_whip": 0.92,
        "sp_home_ip": 28.1,
        "sp_away_ip": 25.1,
        "sp_home_source": "last_30d",
        "sp_away_source": "last_30d",
        "h_bat_source": "last_30d",
        "a_bat_source": "last_30d",
        "h_bull_tax": 0.0,
        "a_bull_tax": 0.0,
        "h_bull_detail": [],
        "a_bull_detail": [],
        "h_home_wr": 0.473,
        "a_away_wr": 0.499,
        "ump_bias": 0.0,
        "mkt_home_p": 0.4455,
        "mkt_away_p": 0.5545,
        "book_lines": {},
        "best_book": null,
        "best_book_ml": null
      },
      "market_edge": {
        "best_bet": "NO EDGE",
        "f5_bet": null,
        "ev_percent": 0.0,
        "kelly_stake": "0%",
        "tier": "SKIP",
        "bet_side": null,
        "signals": [
          "LINEUP_UNCONFIRMED",
          "SINGLE_BOOK_ONLY"
        ]
      },
      "math": {
        "base_pyth_p": 0.4637,
        "prop_adj": -0.0474,
        "ump_adj": 0.0,
        "h_fatigue_tax": 0.0,
        "a_fatigue_tax": 0.0,
        "final_home_p": 0.4163,
        "mkt_home_p": 0.4455,
        "h_home_wr": 0.473,
        "a_away_wr": 0.499,
        "park_factor": 1.0,
        "ump_bias": 0.0,
        "sp_suppress_h": 0.3114,
        "sp_suppress_a": 0.316
      }
    },
    {
      "game_metadata": {
        "game_id": "2026-06-24-KC-TB",
        "game_pk": "822965",
        "home": "TB",
        "away": "KC",
        "home_full": "Tampa Bay Rays",
        "away_full": "Kansas City Royals",
        "home_sp": "Griffin Jax",
        "away_sp": "Noah Cameron",
        "start_time": "2026-06-24T22:40:00Z",
        "venue": "Tropicana Field",
        "park_factor": 0.908,
        "weather": {
          "temp_f": 90.8,
          "wind_mph": 6.0,
          "wind_dir": "NW",
          "condition": "Clear",
          "provisional": false
        },
        "umpire": "Mike Muchlinski",
        "lineup_confirmed": true,
        "status": "scheduled",
        "score": "Scheduled",
        "result": null
      },
      "projections": {
        "fair_home_ml": -161,
        "fair_away_ml": 161,
        "fair_home_p": 0.616,
        "fair_away_p": 0.384,
        "fair_f5_p": 0.561,
        "proj_total": 8.4,
        "home_proj_runs": 4.34,
        "away_proj_runs": 4.11,
        "home_woba": 0.3135,
        "away_woba": 0.3355,
        "sp_home_era": 3.67,
        "sp_away_era": 3.32,
        "sp_home_fip": 4.78,
        "sp_away_fip": 3.13,
        "sp_home_k9": 8.45,
        "sp_away_k9": 8.63,
        "sp_home_bb9": 3.31,
        "sp_away_bb9": 1.0,
        "sp_home_whip": 1.31,
        "sp_away_whip": 0.96,
        "sp_home_ip": 49.0,
        "sp_away_ip": 27.1,
        "sp_home_source": "season_2026",
        "sp_away_source": "last_30d",
        "h_bat_source": "last_30d",
        "a_bat_source": "last_30d",
        "h_bull_tax": 0.0,
        "a_bull_tax": 0.0,
        "h_bull_detail": [],
        "a_bull_detail": [],
        "h_home_wr": 0.606,
        "a_away_wr": 0.356,
        "ump_bias": 0.0,
        "mkt_home_p": 0.5545,
        "mkt_away_p": 0.4455,
        "book_lines": {},
        "best_book": null,
        "best_book_ml": null
      },
      "market_edge": {
        "best_bet": "NO EDGE",
        "f5_bet": null,
        "ev_percent": 0.0,
        "kelly_stake": "0%",
        "tier": "SKIP",
        "bet_side": null,
        "signals": [
          "LINEUPS_CONFIRMED",
          "PITCHERS_PARK",
          "HOT_WEATHER",
          "SINGLE_BOOK_ONLY"
        ]
      },
      "math": {
        "base_pyth_p": 0.5249,
        "prop_adj": 0.0913,
        "ump_adj": 0.0,
        "h_fatigue_tax": 0.0,
        "a_fatigue_tax": 0.0,
        "final_home_p": 0.6162,
        "mkt_home_p": 0.5545,
        "h_home_wr": 0.606,
        "a_away_wr": 0.356,
        "park_factor": 0.908,
        "ump_bias": 0.0,
        "sp_suppress_h": 0.3097,
        "sp_suppress_a": 0.3062
      }
    },
    {
      "game_metadata": {
        "game_id": "2026-06-24-NYY-DET",
        "game_pk": "824259",
        "home": "DET",
        "away": "NYY",
        "home_full": "Detroit Tigers",
        "away_full": "New York Yankees",
        "home_sp": "Tarik Skubal",
        "away_sp": "Ryan Weathers",
        "start_time": "2026-06-24T22:40:00Z",
        "venue": "Comerica Park",
        "park_factor": 1.0,
        "weather": {
          "temp_f": 74.9,
          "wind_mph": 1.0,
          "wind_dir": "S",
          "condition": "Clouds",
          "provisional": false
        },
        "umpire": "TBD",
        "lineup_confirmed": false,
        "status": "scheduled",
        "score": "Scheduled",
        "result": null
      },
      "projections": {
        "fair_home_ml": 134,
        "fair_away_ml": -134,
        "fair_home_p": 0.428,
        "fair_away_p": 0.572,
        "fair_f5_p": 0.475,
        "proj_total": 9.3,
        "home_proj_runs": 4.71,
        "away_proj_runs": 4.64,
        "home_woba": 0.3324,
        "away_woba": 0.348,
        "sp_home_era": 3.02,
        "sp_away_era": 4.13,
        "sp_home_fip": 2.81,
        "sp_away_fip": 4.4,
        "sp_home_k9": 9.56,
        "sp_away_k9": 9.93,
        "sp_home_bb9": 1.34,
        "sp_away_bb9": 2.45,
        "sp_home_whip": 1.02,
        "sp_away_whip": 1.13,
        "sp_home_ip": 53.2,
        "sp_away_ip": 80.2,
        "sp_home_source": "season_2026",
        "sp_away_source": "season_2026",
        "h_bat_source": "last_30d",
        "a_bat_source": "last_30d",
        "h_bull_tax": 0.0,
        "a_bull_tax": 0.0,
        "h_bull_detail": [],
        "a_bull_detail": [],
        "h_home_wr": 0.455,
        "a_away_wr": 0.545,
        "ump_bias": 0.0,
        "mkt_home_p": 0.5487,
        "mkt_away_p": 0.4513,
        "book_lines": {},
        "best_book": null,
        "best_book_ml": null
      },
      "market_edge": {
        "best_bet": "NO EDGE",
        "f5_bet": null,
        "ev_percent": 0.0,
        "kelly_stake": "0%",
        "tier": "SKIP",
        "bet_side": null,
        "signals": [
          "LINEUP_UNCONFIRMED"
        ]
      },
      "math": {
        "base_pyth_p": 0.5068,
        "prop_adj": -0.079,
        "ump_adj": 0.0,
        "h_fatigue_tax": 0.0,
        "a_fatigue_tax": 0.0,
        "final_home_p": 0.4278,
        "mkt_home_p": 0.5487,
        "h_home_wr": 0.455,
        "a_away_wr": 0.545,
        "park_factor": 1.0,
        "ump_bias": 0.0,
        "sp_suppress_h": 0.3032,
        "sp_suppress_a": 0.3143
      }
    },
    {
      "game_metadata": {
        "game_id": "2026-06-24-PHI-WSH",
        "game_pk": "822719",
        "home": "WSH",
        "away": "PHI",
        "home_full": "Washington Nationals",
        "away_full": "Philadelphia Phillies",
        "home_sp": "Miles Mikolas",
        "away_sp": "Aaron Nola",
        "start_time": "2026-06-24T22:45:00Z",
        "venue": "Nationals Park",
        "park_factor": 0.996,
        "weather": {
          "temp_f": 83.7,
          "wind_mph": 5.0,
          "wind_dir": "W",
          "condition": "Clear",
          "provisional": false
        },
        "umpire": "TBD",
        "lineup_confirmed": false,
        "status": "scheduled",
        "score": "Scheduled",
        "result": null
      },
      "projections": {
        "fair_home_ml": 132,
        "fair_away_ml": -132,
        "fair_home_p": 0.43,
        "fair_away_p": 0.57,
        "fair_f5_p": 0.459,
        "proj_total": 9.5,
        "home_proj_runs": 4.63,
        "away_proj_runs": 4.86,
        "home_woba": 0.3354,
        "away_woba": 0.323,
        "sp_home_era": 4.43,
        "sp_away_era": 5.71,
        "sp_home_fip": 5.06,
        "sp_away_fip": 4.71,
        "sp_home_k9": 4.09,
        "sp_away_k9": 9.16,
        "sp_home_bb9": 1.02,
        "sp_away_bb9": 2.97,
        "sp_home_whip": 1.14,
        "sp_away_whip": 1.48,
        "sp_home_ip": 26.4,
        "sp_away_ip": 75.2,
        "sp_home_source": "last_30d",
        "sp_away_source": "season_2026",
        "h_bat_source": "last_30d",
        "a_bat_source": "last_30d",
        "h_bull_tax": 0.0,
        "a_bull_tax": 0.0,
        "h_bull_detail": [],
        "a_bull_detail": [],
        "h_home_wr": 0.439,
        "a_away_wr": 0.466,
        "ump_bias": 0.0,
        "mkt_home_p": 0.3752,
        "mkt_away_p": 0.6248,
        "book_lines": {},
        "best_book": null,
        "best_book_ml": null
      },
      "market_edge": {
        "best_bet": "NO EDGE",
        "f5_bet": null,
        "ev_percent": 0.0,
        "kelly_stake": "0%",
        "tier": "SKIP",
        "bet_side": null,
        "signals": [
          "LINEUP_UNCONFIRMED",
          "SINGLE_BOOK_ONLY"
        ]
      },
      "math": {
        "base_pyth_p": 0.4778,
        "prop_adj": -0.0475,
        "ump_adj": 0.0,
        "h_fatigue_tax": 0.0,
        "a_fatigue_tax": 0.0,
        "final_home_p": 0.4304,
        "mkt_home_p": 0.3752,
        "h_home_wr": 0.439,
        "a_away_wr": 0.466,
        "park_factor": 0.996,
        "ump_bias": 0.0,
        "sp_suppress_h": 0.3173,
        "sp_suppress_a": 0.3301
      }
    },
    {
      "game_metadata": {
        "game_id": "2026-06-24-HOU-TOR",
        "game_pk": "822798",
        "home": "TOR",
        "away": "HOU",
        "home_full": "Toronto Blue Jays",
        "away_full": "Houston Astros",
        "home_sp": "Trey Yesavage",
        "away_sp": "Mike Burrows",
        "start_time": "2026-06-24T23:07:00Z",
        "venue": "Rogers Centre",
        "park_factor": 1.042,
        "weather": {
          "temp_f": 76.2,
          "wind_mph": 2.0,
          "wind_dir": "S",
          "condition": "Clouds",
          "provisional": false
        },
        "umpire": "TBD",
        "lineup_confirmed": false,
        "status": "scheduled",
        "score": "Scheduled",
        "result": null
      },
      "projections": {
        "fair_home_ml": 135,
        "fair_away_ml": -135,
        "fair_home_p": 0.425,
        "fair_away_p": 0.575,
        "fair_f5_p": 0.467,
        "proj_total": 10.0,
        "home_proj_runs": 4.96,
        "away_proj_runs": 5.01,
        "home_woba": 0.3342,
        "away_woba": 0.3251,
        "sp_home_era": 6.32,
        "sp_away_era": 5.79,
        "sp_home_fip": 5.56,
        "sp_away_fip": 5.71,
        "sp_home_k9": 7.58,
        "sp_away_k9": 7.49,
        "sp_home_bb9": 5.37,
        "sp_away_bb9": 3.4,
        "sp_home_whip": 1.3,
        "sp_away_whip": 1.58,
        "sp_home_ip": 28.5,
        "sp_away_ip": 79.1,
        "sp_home_source": "last_30d",
        "sp_away_source": "season_2026",
        "h_bat_source": "last_30d",
        "a_bat_source": "last_30d",
        "h_bull_tax": 0.0,
        "a_bull_tax": 0.0,
        "h_bull_detail": [],
        "a_bull_detail": [],
        "h_home_wr": 0.521,
        "a_away_wr": 0.593,
        "ump_bias": 0.0,
        "mkt_home_p": 0.5652,
        "mkt_away_p": 0.4348,
        "book_lines": {},
        "best_book": null,
        "best_book_ml": null
      },
      "market_edge": {
        "best_bet": "NO EDGE",
        "f5_bet": null,
        "ev_percent": 0.0,
        "kelly_stake": "0%",
        "tier": "SKIP",
        "bet_side": null,
        "signals": [
          "LINEUP_UNCONFIRMED"
        ]
      },
      "math": {
        "base_pyth_p": 0.4954,
        "prop_adj": -0.0701,
        "ump_adj": 0.0,
        "h_fatigue_tax": 0.0,
        "a_fatigue_tax": 0.0,
        "final_home_p": 0.4253,
        "mkt_home_p": 0.5652,
        "h_home_wr": 0.521,
        "a_away_wr": 0.593,
        "park_factor": 1.042,
        "ump_bias": 0.0,
        "sp_suppress_h": 0.3362,
        "sp_suppress_a": 0.3309
      }
    },
    {
      "game_metadata": {
        "game_id": "2026-06-24-MIL-CIN",
        "game_pk": "824500",
        "home": "CIN",
        "away": "MIL",
        "home_full": "Cincinnati Reds",
        "away_full": "Milwaukee Brewers",
        "home_sp": "Rhett Lowder",
        "away_sp": "Shane Drohan",
        "start_time": "2026-06-24T23:10:00Z",
        "venue": "Great American Ball Park",
        "park_factor": 1.037,
        "weather": {
          "temp_f": 81.1,
          "wind_mph": 2.0,
          "wind_dir": "SE",
          "condition": "Clear",
          "provisional": false
        },
        "umpire": "Adam Hamari",
        "lineup_confirmed": false,
        "status": "scheduled",
        "score": "Scheduled",
        "result": null
      },
      "projections": {
        "fair_home_ml": 105,
        "fair_away_ml": -105,
        "fair_home_p": 0.488,
        "fair_away_p": 0.512,
        "fair_f5_p": 0.527,
        "proj_total": 9.5,
        "home_proj_runs": 5.03,
        "away_proj_runs": 4.47,
        "home_woba": 0.3011,
        "away_woba": 0.3418,
        "sp_home_era": 4.82,
        "sp_away_era": 3.4,
        "sp_home_fip": 4.53,
        "sp_away_fip": 3.23,
        "sp_home_k9": 7.22,
        "sp_away_k9": 8.87,
        "sp_home_bb9": 4.82,
        "sp_away_bb9": 2.64,
        "sp_home_whip": 1.45,
        "sp_away_whip": 1.17,
        "sp_home_ip": 52.1,
        "sp_away_ip": 47.2,
        "sp_home_source": "season_2026",
        "sp_away_source": "season_2026",
        "h_bat_source": "last_30d",
        "a_bat_source": "last_30d",
        "h_bull_tax": 0.0,
        "a_bull_tax": 0.0,
        "h_bull_detail": [],
        "a_bull_detail": [],
        "h_home_wr": 0.466,
        "a_away_wr": 0.529,
        "ump_bias": 0.0,
        "mkt_home_p": 0.4544,
        "mkt_away_p": 0.5456,
        "book_lines": {},
        "best_book": null,
        "best_book_ml": null
      },
      "market_edge": {
        "best_bet": "NO EDGE",
        "f5_bet": null,
        "ev_percent": 0.0,
        "kelly_stake": "0%",
        "tier": "SKIP",
        "bet_side": null,
        "signals": [
          "LINEUP_UNCONFIRMED"
        ]
      },
      "math": {
        "base_pyth_p": 0.5538,
        "prop_adj": -0.0658,
        "ump_adj": 0.0,
        "h_fatigue_tax": 0.0,
        "a_fatigue_tax": 0.0,
        "final_home_p": 0.488,
        "mkt_home_p": 0.4544,
        "h_home_wr": 0.466,
        "a_away_wr": 0.529,
        "park_factor": 1.037,
        "ump_bias": 0.0,
        "sp_suppress_h": 0.3212,
        "sp_suppress_a": 0.307
      }
    },
    {
      "game_metadata": {
        "game_id": "2026-06-24-LAD-MIN",
        "game_pk": "823691",
        "home": "MIN",
        "away": "LAD",
        "home_full": "Minnesota Twins",
        "away_full": "Los Angeles Dodgers",
        "home_sp": "Joe Ryan",
        "away_sp": "Shohei Ohtani",
        "start_time": "2026-06-24T23:40:00Z",
        "venue": "Target Field",
        "park_factor": 1.051,
        "weather": {
          "temp_f": 76.0,
          "wind_mph": 5.0,
          "wind_dir": "N",
          "condition": "Clouds",
          "provisional": false
        },
        "umpire": "Ryan Additon",
        "lineup_confirmed": false,
        "status": "scheduled",
        "score": "Scheduled",
        "result": null
      },
      "projections": {
        "fair_home_ml": 116,
        "fair_away_ml": -116,
        "fair_home_p": 0.464,
        "fair_away_p": 0.536,
        "fair_f5_p": 0.502,
        "proj_total": 9.7,
        "home_proj_runs": 4.98,
        "away_proj_runs": 4.68,
        "home_woba": 0.3343,
        "away_woba": 0.3505,
        "sp_home_era": 2.98,
        "sp_away_era": 1.47,
        "sp_home_fip": 3.4,
        "sp_away_fip": 2.72,
        "sp_home_k9": 11.32,
        "sp_away_k9": 9.53,
        "sp_home_bb9": 1.19,
        "sp_away_bb9": 2.69,
        "sp_home_whip": 1.06,
        "sp_away_whip": 0.88,
        "sp_home_ip": 30.2,
        "sp_away_ip": 73.2,
        "sp_home_source": "last_30d",
        "sp_away_source": "season_2026",
        "h_bat_source": "last_30d",
        "a_bat_source": "last_30d",
        "h_bull_tax": 0.0,
        "a_bull_tax": 0.0,
        "h_bull_detail": [],
        "a_bull_detail": [],
        "h_home_wr": 0.551,
        "a_away_wr": 0.613,
        "ump_bias": 0.0,
        "mkt_home_p": 0.3891,
        "mkt_away_p": 0.6109,
        "book_lines": {},
        "best_book": null,
        "best_book_ml": null
      },
      "market_edge": {
        "best_bet": "NO EDGE",
        "f5_bet": null,
        "ev_percent": 0.0,
        "kelly_stake": "0%",
        "tier": "SKIP",
        "bet_side": null,
        "signals": [
          "LINEUP_UNCONFIRMED"
        ]
      },
      "math": {
        "base_pyth_p": 0.5284,
        "prop_adj": -0.0648,
        "ump_adj": 0.0,
        "h_fatigue_tax": 0.0,
        "a_fatigue_tax": 0.0,
        "final_home_p": 0.4636,
        "mkt_home_p": 0.3891,
        "h_home_wr": 0.551,
        "a_away_wr": 0.613,
        "park_factor": 1.051,
        "ump_bias": 0.0,
        "sp_suppress_h": 0.3028,
        "sp_suppress_a": 0.2877
      }
    },
    {
      "game_metadata": {
        "game_id": "2026-06-24-ATH-SF",
        "game_pk": "823208",
        "home": "SF",
        "away": "ATH",
        "home_full": "San Francisco Giants",
        "away_full": "Athletics",
        "home_sp": "Tyler Mahle",
        "away_sp": "Gage Jump",
        "start_time": "2026-06-25T01:45:00Z",
        "venue": "Oracle Park",
        "park_factor": 0.888,
        "weather": {
          "temp_f": 62.6,
          "wind_mph": 12.0,
          "wind_dir": "SW",
          "condition": "Clouds",
          "provisional": false
        },
        "umpire": "TBD",
        "lineup_confirmed": false,
        "status": "scheduled",
        "score": "Scheduled",
        "result": null
      },
      "projections": {
        "fair_home_ml": -118,
        "fair_away_ml": 118,
        "fair_home_p": 0.542,
        "fair_away_p": 0.458,
        "fair_f5_p": 0.528,
        "proj_total": 8.1,
        "home_proj_runs": 4.14,
        "away_proj_runs": 3.97,
        "home_woba": 0.3546,
        "away_woba": 0.3442,
        "sp_home_era": 6.04,
        "sp_away_era": 2.39,
        "sp_home_fip": 4.97,
        "sp_away_fip": 2.54,
        "sp_home_k9": 9.05,
        "sp_away_k9": 7.77,
        "sp_home_bb9": 3.81,
        "sp_away_bb9": 2.69,
        "sp_home_whip": 1.54,
        "sp_away_whip": 1.0,
        "sp_home_ip": 56.2,
        "sp_away_ip": 30.1,
        "sp_home_source": "season_2026",
        "sp_away_source": "last_30d",
        "h_bat_source": "last_30d",
        "a_bat_source": "last_30d",
        "h_bull_tax": 0.0,
        "a_bull_tax": 0.0,
        "h_bull_detail": [],
        "a_bull_detail": [],
        "h_home_wr": 0.532,
        "a_away_wr": 0.42,
        "ump_bias": 0.0,
        "mkt_home_p": 0.5427,
        "mkt_away_p": 0.4573,
        "book_lines": {},
        "best_book": null,
        "best_book_ml": null
      },
      "market_edge": {
        "best_bet": "NO EDGE",
        "f5_bet": null,
        "ev_percent": 0.0,
        "kelly_stake": "0%",
        "tier": "SKIP",
        "bet_side": null,
        "signals": [
          "LINEUP_UNCONFIRMED",
          "PITCHERS_PARK",
          "WIND_12.0mph_SW",
          "SINGLE_BOOK_ONLY"
        ]
      },
      "math": {
        "base_pyth_p": 0.5192,
        "prop_adj": 0.0224,
        "ump_adj": 0.0,
        "h_fatigue_tax": 0.0,
        "a_fatigue_tax": 0.0,
        "final_home_p": 0.5416,
        "mkt_home_p": 0.5427,
        "h_home_wr": 0.532,
        "a_away_wr": 0.42,
        "park_factor": 0.888,
        "ump_bias": 0.0,
        "sp_suppress_h": 0.3334,
        "sp_suppress_a": 0.2969
      }
    }
  ]
}